{
  "member": [
    {
      "no": 1,
      "phone": "010-1",
      "name": "Robin",
      "check": "확진",
      "age": "12",
      "room": "1호실"
    },
    {
      "no": 2,
      "phone": "010-2",
      "name": "김이름",
      "check": "정상",
      "age": "25",
      "room": ""
    },
    {
      "no": 3,
      "phone": "010-3",
      "name": "이이름",
      "check": "확진",
      "age": "55",
      "room": "타병원"
    },
    {
      "no": 4,
      "phone": "010-4",
      "name": "최이름",
      "check": "확진",
      "age": "76",
      "room": "타병원"
    },
    {
      "no": 5,
      "phone": "010-5",
      "name": "박이름",
      "check": "확진",
      "age": "69",
      "room": "3호실"
    },
    {
      "no": 6,
      "phone": "010-6",
      "name": "유이름",
      "check": "확진",
      "age": "42",
      "room": "3호실"
    },
    {
      "no": 7,
      "phone": "010-7",
      "name": "Chloe",
      "check": "확진",
      "age": "80",
      "room": "3호실"
    },
    {
      "no": 8,
      "phone": "010-8",
      "name": "강이름",
      "check": "확진",
      "age": "94",
      "room": "3호실"
    },
    {
      "no": 9,
      "phone": "",
      "name": "Yas",
      "check": "",
      "age": "20",
      "room": ""
    }
  ],
  "seq": 10
}